deezer_api/__init__.py
deezer_api/deezer_api.py
deezer_api/deezer_auth.py
deezer_api/deezer_objects.py
deezer_api/deezer_player.py
deezer_playlist_generator-1.0.3.dist-info/LICENSE
deezer_playlist_generator-1.0.3.dist-info/METADATA
deezer_playlist_generator-1.0.3.dist-info/WHEEL
deezer_playlist_generator-1.0.3.dist-info/top_level.txt
deezer_playlist_generator-1.0.3.dist-info/RECORD
