Metadata-Version: 2.1
Name: deezer-playlist-generator
Version: 1.0.3
Summary: Library for working with Deezer API for creating a playlist by your preferences in Deezer
Home-page: https://github.com/ElinaValieva/deezer-playlist-generator
Author: Valieva Elina
Author-email: valievaelinaaa@gmail.com
License: MIT
Download-URL: https://github.com/browniebroke/deezer-python/tarball/1.0.3
Platform: UNKNOWN
Classifier: Programming Language :: Python
Classifier: Programming Language :: Python :: 3
Classifier: Programming Language :: Python :: 3.5
Classifier: Programming Language :: Python :: 3.6
Classifier: Programming Language :: Python :: 3.7
Classifier: Programming Language :: Python :: 3.8
Classifier: Programming Language :: Python :: 3 :: Only
Classifier: Topic :: Software Development :: Libraries :: Python Modules
Requires-Python: >=3.5
Requires-Dist: requests (==2.23.0)
Requires-Dist: tqdm (==4.46.0)
Requires-Dist: pygame (==2.0.0.dev8)
Requires-Dist: Pillow (==7.1.2)
